face_tagger/__init__.py
face_tagger/classifier.py
face_tagger/detector.py
face_tagger/embedder.py
face_tagger/face_tagger.py
face_tagger/utils.py
face_tagger/models/__init__.py
face_tagger/models/image_object.py
face_tagger-1.0.4.dist-info/METADATA
face_tagger-1.0.4.dist-info/WHEEL
face_tagger-1.0.4.dist-info/licenses/LICENSE
face_tagger-1.0.4.dist-info/RECORD
