Metadata-Version: 2.1
Name: face_tagger
Version: 1.0.4
Summary: A library for face recognition in multiple images and classification of photos containing each individual.
Project-URL: Homepage, https://github.com/Face-Tagger
Project-URL: Bug Tracker, https://github.com/Face-Tagger/facetagger-lib/issues
Author-email: Sohn YoungJin <sonkim1001@naver.com>, Bae SungJoon <clcc001@naver.com>, Yoon JongBeom <home99032@naver.com>, Choi JunHwan <csd100j@gmail.com>
License-File: LICENSE
Classifier: License :: OSI Approved :: MIT License
Classifier: Operating System :: OS Independent
Classifier: Programming Language :: Python :: 3
Requires-Python: >=3.9
Requires-Dist: absl-py==1.4.0
Requires-Dist: astunparse==1.6.3
Requires-Dist: cachetools==5.3.1
Requires-Dist: certifi==2023.7.22
Requires-Dist: charset-normalizer==3.2.0
Requires-Dist: cython==0.29.36
Requires-Dist: facenet-pytorch==2.5.3
Requires-Dist: filelock==3.12.3
Requires-Dist: flatbuffers==23.5.26
Requires-Dist: gast==0.4.0
Requires-Dist: google-auth-oauthlib==1.0.0
Requires-Dist: google-auth==2.22.0
Requires-Dist: google-pasta==0.2.0
Requires-Dist: grpcio==1.57.0
Requires-Dist: h5py==3.9.0
Requires-Dist: hdbscan==0.8.33
Requires-Dist: idna==3.4
Requires-Dist: jinja2==3.1.2
Requires-Dist: joblib==1.3.2
Requires-Dist: keras==2.13.1
Requires-Dist: libclang==16.0.6
Requires-Dist: markdown==3.4.4
Requires-Dist: markupsafe==2.1.3
Requires-Dist: mpmath==1.3.0
Requires-Dist: mtcnn==0.1.1
Requires-Dist: networkx==3.1
Requires-Dist: numpy==1.24.3
Requires-Dist: oauthlib==3.2.2
Requires-Dist: opencv-python==4.8.0.74
Requires-Dist: opt-einsum==3.3.0
Requires-Dist: packaging==23.1
Requires-Dist: pillow==10.0.0
Requires-Dist: protobuf==4.24.2
Requires-Dist: pyasn1-modules==0.3.0
Requires-Dist: pyasn1==0.5.0
Requires-Dist: requests-oauthlib==1.3.1
Requires-Dist: requests==2.31.0
Requires-Dist: rsa==4.9
Requires-Dist: scikit-learn==1.3.0
Requires-Dist: scipy==1.11.2
Requires-Dist: six==1.16.0
Requires-Dist: sympy==1.12
Requires-Dist: tensorboard-data-server==0.7.1
Requires-Dist: tensorboard==2.13.0
Requires-Dist: tensorflow-cpu==2.13.0
Requires-Dist: tensorflow-estimator==2.13.0
Requires-Dist: tensorflow-io-gcs-filesystem==0.31.0
Requires-Dist: tensorflow==2.13.0
Requires-Dist: termcolor==2.3.0
Requires-Dist: threadpoolctl==3.2.0
Requires-Dist: torch==2.0.1
Requires-Dist: torchvision==0.15.2
Requires-Dist: typing-extensions==4.5.0
Requires-Dist: urllib3==1.26.16
Requires-Dist: werkzeug==2.3.7
Requires-Dist: wrapt==1.15.0
